{
  "description": "项目私有配置文件。此文件中的内容将覆盖 project.config.json 中的相同字段。项目的改动优先同步到此文件中。详见文档：https://developers.weixin.qq.com/miniprogram/dev/devtools/projectconfig.html",
  "projectname": "ofo-applet-master",
  "setting": {
    "compileHotReLoad": true,
    "urlCheck": false
  },
  "libVersion": "development",
  "condition": {
    "miniprogram": {
      "list": [
        {
          "name": "pages/face/index",
          "pathName": "pages/face/index",
          "query": "",
          "launchMode": "default",
          "scene": null
        },
        {
          "name": "pages/wallet/index",
          "pathName": "pages/wallet/index",
          "query": "",
          "launchMode": "default",
          "scene": null
        },
        {
          "name": "pages/zhuce/index",
          "pathName": "pages/zhuce/index",
          "query": "",
          "launchMode": "default",
          "scene": null
        },
        {
          "name": "pages/my2/index",
          "pathName": "pages/my2/index",
          "query": "",
          "launchMode": "default",
          "scene": null
        }
      ]
    }
  }
}